oryn-2.1.dist-info/METADATA
oryn-2.1.dist-info/WHEEL
oryn-2.1.dist-info/RECORD
oryn/__init__.py
oryn/__main__.py
oryn/build.py
oryn/inclusion.py
oryn/matching.py
oryn/metadata.py
