Metadata-Version: 2.4
Name: oryn
Version: 2.1
Requires-Python: ~=3.12
Summary: PEP 517-compliant build backend
Requires-Dist: packaging==25.0
License-Expression: EUPL-1.2
Project-URL: Repository, https://github.com/slietar/oryn
